flask_mauth/__init__.py
flask_mauth/__version__.py
flask_mauth/auth.py
flask_mauth/exceptions.py
flask_mauth/settings.py
flask_mauth/cacher/__init__.py
flask_mauth/cacher/security_token_cacher.py
flask_mauth/mauth/__init__.py
flask_mauth/mauth/authenticators.py
flask_mauth/mauth/signature.py
flask_mauth/rsa_public_decrypt/__init__.py
flask_mauth/rsa_public_decrypt/rsa_decrypt.py
Flask_MAuth-1.1.dist-info/top_level.txt
Flask_MAuth-1.1.dist-info/METADATA
Flask_MAuth-1.1.dist-info/DESCRIPTION.rst
Flask_MAuth-1.1.dist-info/metadata.json
Flask_MAuth-1.1.dist-info/WHEEL
Flask_MAuth-1.1.dist-info/RECORD
